pipcoloringliberyV2/__init__.py
pipcoloringliberyV2-1.0.0.dist-info/METADATA
pipcoloringliberyV2-1.0.0.dist-info/WHEEL
pipcoloringliberyV2-1.0.0.dist-info/top_level.txt
pipcoloringliberyV2-1.0.0.dist-info/RECORD
