Metadata-Version: 2.1
Name: pipcoloringliberyV2
Version: 1.0.0
Summary: Colors for Python
Home-page: UNKNOWN
Author: Bluescreen
Author-email: nick.faltermeier@gmx.de
License: UNKNOWN
Keywords: python
Platform: UNKNOWN
Classifier: Operating System :: Microsoft :: Windows
